openfiles/__init__.py
openfiles/client.py
openfiles/exceptions.py
openfiles/models.py
openfiles-1.1.1.dist-info/licenses/LICENSE
openfiles-1.1.1.dist-info/METADATA
openfiles-1.1.1.dist-info/WHEEL
openfiles-1.1.1.dist-info/top_level.txt
openfiles-1.1.1.dist-info/RECORD
